rinzler/__init__.py
rinzler/auth/__init__.py
rinzler/auth/base_auth_service.py
rinzler/core/__init__.py
rinzler/core/app.py
rinzler/core/main_controller.py
rinzler/core/request.py
rinzler/core/response.py
rinzler/core/route_mapping.py
rinzler/core/router.py
rinzler/exceptions/__init__.py
rinzler/exceptions/auth_exception.py
rinzler/exceptions/conflict_exception.py
rinzler/exceptions/content_too_large_exception.py
rinzler/exceptions/expectation_failed_exception.py
rinzler/exceptions/failed_dependency_exception.py
rinzler/exceptions/gone_exception.py
rinzler/exceptions/i_am_a_teapot_exception.py
rinzler/exceptions/internal_exception.py
rinzler/exceptions/invalid_input_exception.py
rinzler/exceptions/not_allowed_exception.py
rinzler/exceptions/not_found_exception.py
rinzler/exceptions/precondition_failed_exception.py
rinzler/exceptions/precondition_required_exception.py
rinzler/exceptions/service_unavailable_exception.py
rinzler/exceptions/unacceptable_input_exception.py
rinzler/exceptions/unauthorized_exception.py
rinzler/logger/__init__.py
rinzler/logger/log.py
rinzler-3.1.0.dist-info/LICENSE.txt
rinzler-3.1.0.dist-info/METADATA
rinzler-3.1.0.dist-info/WHEEL
rinzler-3.1.0.dist-info/top_level.txt
rinzler-3.1.0.dist-info/RECORD
