Metadata-Version: 2.2
Name: rinzler
Version: 3.1.0
Summary: Django-based REST API Framework
Home-page: https://github.com/feliphebueno/Rinzler
Author: Rinzler
Author-email: feliphezion@gmail.com
License: MIT
Keywords: rest,api,framework,django
Classifier: Development Status :: 3 - Alpha
Classifier: Intended Audience :: Developers
Classifier: Topic :: Software Development
Classifier: License :: OSI Approved :: MIT License
Classifier: Programming Language :: Python :: 3.9
Classifier: Programming Language :: Python :: 3.10
Classifier: Programming Language :: Python :: 3.11
Requires-Python: >=3.8
License-File: LICENSE.txt
Requires-Dist: Django~=5.1
Requires-Dist: PyYAML==6.0.2
Requires-Dist: setuptools==75.8.2
Dynamic: author
Dynamic: author-email
Dynamic: classifier
Dynamic: description
Dynamic: description-content-type
Dynamic: home-page
Dynamic: keywords
Dynamic: license
Dynamic: requires-dist
Dynamic: requires-python
Dynamic: summary
